{
	"users": [
		{
			"id": 1,
			"firstName": "Bridget",
			"lastName": "Rodriguez",
			"email": "itzel73@gmail.com",
			"status": false,
			"birthday": "2024-02-06T07:34:08.195Z",
			"skills": [
				"refine",
				"svelte",
				".net"
			],
			"avatar": [
				{
					"name": "Bridget.jpg",
					"percent": 100,
					"size": 40088,
					"status": "done",
					"type": "image/jpeg",
					"uid": "rc-upload-1715285179832",
					"url": "https://cloudflare-ipfs.com/ipfs/Qmd3W5DuhgHirLHGVixi6V76LhCkZUz6pnFt5AJBiyvHye/avatar/216.jpg"
				}
			]
		},
		{
			"id": 2,
			"firstName": "Davion",
			"lastName": "Botsford",
			"email": "graciela42@yahoo.com",
			"status": false,
			"birthday": "2023-06-20T16:41:43.919Z",
			"skills": [
				"postgresql",
				"swift",
				"react"
			],
			"avatar": [
				{
					"name": "Davion.jpg",
					"percent": 100,
					"size": 40088,
					"status": "done",
					"type": "image/jpeg",
					"uid": "rc-upload-1715285179832",
					"url": "https://cloudflare-ipfs.com/ipfs/Qmd3W5DuhgHirLHGVixi6V76LhCkZUz6pnFt5AJBiyvHye/avatar/286.jpg"
				}
			]
		},
		{
			"id": 3,
			"firstName": "Meghan",
			"lastName": "O'Reilly",
			"email": "nat79@yahoo.com",
			"status": false,
			"birthday": "2023-11-02T05:04:01.180Z",
			"skills": [
				"swift",
				"svelte",
				"postgresql"
			],
			"avatar": [
				{
					"name": "Meghan.jpg",
					"percent": 100,
					"size": 40088,
					"status": "done",
					"type": "image/jpeg",
					"uid": "rc-upload-1715285179832",
					"url": "https://cloudflare-ipfs.com/ipfs/Qmd3W5DuhgHirLHGVixi6V76LhCkZUz6pnFt5AJBiyvHye/avatar/488.jpg"
				}
			]
		},
		{
			"id": 4,
			"firstName": "Ernesto",
			"lastName": "Thiel",
			"email": "dianna6@gmail.com",
			"status": true,
			"birthday": "2023-11-27T05:45:36.342Z",
			"skills": [
				"javascript",
				"refine",
				"tailwind"
			],
			"avatar": [
				{
					"name": "Ernesto.jpg",
					"percent": 100,
					"size": 40088,
					"status": "done",
					"type": "image/jpeg",
					"uid": "rc-upload-1715285179832",
					"url": "https://cloudflare-ipfs.com/ipfs/Qmd3W5DuhgHirLHGVixi6V76LhCkZUz6pnFt5AJBiyvHye/avatar/572.jpg"
				}
			]
		},
		{
			"id": 5,
			"firstName": "Augustus",
			"lastName": "Hansen",
			"email": "kennedi67@yahoo.com",
			"status": true,
			"birthday": "2023-09-17T22:49:01.235Z",
			"skills": [
				"refine",
				"swift",
				"postgresql"
			],
			"avatar": [
				{
					"name": "Augustus.jpg",
					"percent": 100,
					"size": 40088,
					"status": "done",
					"type": "image/jpeg",
					"uid": "rc-upload-1715285179832",
					"url": "https://cloudflare-ipfs.com/ipfs/Qmd3W5DuhgHirLHGVixi6V76LhCkZUz6pnFt5AJBiyvHye/avatar/716.jpg"
				}
			]
		}
	],
	"categories": [
		{
			"id": 1,
			"title": "Laptops & Desktops"
		},
		{
			"id": 2,
			"title": "Smartphones & Tablets"
		},
		{
			"id": 3,
			"title": "Audio & Video"
		},
		{
			"id": 4,
			"title": "Gaming"
		},
		{
			"id": 5,
			"title": "Home & Kitchen"
		},
		{
			"id": 6,
			"title": "Office & Supplies"
		},
		{
			"id": 7,
			"title": "Books & Magazines"
		},
		{
			"id": 8,
			"title": "Music & Instruments"
		},
		{
			"id": 9,
			"title": "Health & Fitness"
		},
		{
			"id": 10,
			"title": "Clothing & Accessories"
		},
		{
			"id": 11,
			"title": "Travel & Outdoor"
		},
		{
			"id": 12,
			"title": "Toys & Games"
		},
		{
			"id": 13,
			"title": "Beauty & Personal Care"
		},
		{
			"id": 14,
			"title": "Sports"
		},
		{
			"id": 15,
			"title": "Automotive & Industrial"
		},
		{
			"title": "Nova categoria AG",
			"id": 16
		},
		{
			"title": "teste post",
			"id": 17
		}
	],
	"blog_posts": [
		{
			"id": 1,
			"title": "Non Quas Vitae",
			"content": "Aut id assumenda. Possimus necessitatibus animi natus ipsam perferendis adipisci. Vel voluptas ab saepe. Molestiae itaque reiciendis ut harum voluptates. Aut aspernatur nostrum repellat consequatur et suscipit exercitationem. Assumenda ad accusamus velit dolorem blanditiis. Soluta dolorum officiis sint iste. Est expedita non sapiente qui est. Qui officiis voluptatem nihil architecto perspiciatis sit tempore quos est. Nemo consequuntur facilis est.",
			"category": {
				"id": 14
			},
			"status": "rejected",
			"createdAt": "2023-02-26T15:08:43.248Z"
		},
		{
			"id": 2,
			"title": "Officiis Eum Velit",
			"content": "Quis earum enim dolores officia deleniti est ab eum blanditiis. Beatae sed voluptates alias cum ut voluptatem est et. Dolor ipsa ut aperiam dolorem molestias modi. Iure minima aliquam quaerat debitis nesciunt vel voluptatem. Dolor in nam accusantium. Ipsum at dolorum cupiditate. Voluptatem vero aut et. Nemo et incidunt nihil doloremque. Quasi quis porro. Omnis autem et beatae non ipsa ea dolores accusamus.",
			"category": {
				"id": 5
			},
			"status": "rejected",
			"createdAt": "2024-03-14T20:48:17.774Z"
		},
		{
			"id": 3,
			"title": "Facilis Animi Rerum",
			"content": "Voluptas cum natus commodi eum dolores autem. Nemo sed culpa cum omnis. Quia expedita id et distinctio qui est ut ratione itaque. Autem dolorem eos suscipit quisquam. Sapiente perferendis et asperiores qui saepe voluptate id. Qui facere harum blanditiis quia optio sit dolor. Blanditiis sed eos. Quae eaque corporis iste eius qui nostrum. Adipisci est omnis dolor exercitationem sunt consequuntur. Odio et est temporibus et assumenda aut.",
			"category": {
				"id": 6
			},
			"status": "published",
			"createdAt": "2023-08-01T17:30:33.639Z"
		},
		{
			"id": 4,
			"title": "Itaque Fuga Aut",
			"content": "Ipsam sed pariatur sunt omnis voluptate similique voluptate. Eos minima et culpa sunt et libero. Perferendis voluptas assumenda dolorem illo eveniet veritatis est cumque deleniti. Et consequatur voluptatem quo expedita atque nemo ipsum. Ut recusandae impedit dolores fuga eum. Pariatur minima aliquam quas qui vero harum non rerum aut. Et totam pariatur autem quia libero enim. Aliquid pariatur repudiandae sunt saepe omnis necessitatibus esse cupiditate. Officia adipisci magnam reiciendis. Aliquid qui et et temporibus labore.",
			"category": {
				"id": 3
			},
			"status": "rejected",
			"createdAt": "2024-05-03T22:22:01.932Z"
		},
		{
			"id": 5,
			"title": "Aut Aut Consectetur",
			"content": "Et sint et inventore molestiae magnam consequatur. Accusantium architecto et in possimus. Explicabo omnis praesentium. Sapiente earum accusantium fugiat exercitationem voluptatum distinctio autem excepturi. Excepturi nemo accusamus enim dolor aut dignissimos voluptas quis et. Quia doloremque fuga. Porro omnis quasi est distinctio voluptatem qui repudiandae reprehenderit. Nam sit corrupti vel autem. Aliquam iste animi velit provident deleniti. Quae id pariatur aut non voluptatem aliquam perferendis ut magnam.",
			"category": {
				"id": 14
			},
			"status": "draft",
			"createdAt": "2023-09-01T05:09:48.144Z"
		},
		{
			"id": 6,
			"title": "Provident Quis Omnis",
			"content": "Sunt numquam voluptates ut earum et. Vitae doloribus quae enim sed eaque temporibus voluptates quidem. Ex tenetur tempora voluptatem doloremque et. Sit sunt tenetur. Quae asperiores ea veniam tenetur quis quas totam. Consequatur ut dolore aliquam provident ut dolores asperiores fugiat ad. Sunt quo qui ab sint atque et enim saepe. Aliquam et ad quia tempore temporibus necessitatibus et deserunt. Consequatur cumque perferendis consequuntur doloremque rerum aut labore placeat quis. Quibusdam saepe exercitationem velit et.",
			"category": {
				"id": 4
			},
			"status": "rejected",
			"createdAt": "2022-10-20T01:15:04.391Z"
		},
		{
			"id": 7,
			"title": "Doloribus Consequuntur Quos",
			"content": "Et deserunt rerum. Rerum quaerat possimus architecto. Labore enim dolore. Illum autem necessitatibus expedita. Assumenda dignissimos dolores qui omnis saepe autem minima sit. Qui eum illum qui optio. Qui soluta doloribus ducimus fuga est nihil vitae tempora. Possimus quisquam cumque quibusdam sunt dicta dolorem voluptatem numquam adipisci. Distinctio et eos et molestias esse in ut. Similique nisi distinctio ab alias et aut molestias natus error.",
			"category": {
				"id": 11
			},
			"status": "draft",
			"createdAt": "2023-01-10T18:24:11.425Z"
		},
		{
			"id": 8,
			"title": "Totam Nisi Autem",
			"content": "Qui deserunt nisi occaecati. Ad non id fugit vel voluptatibus dolorem. Et consequatur sequi id. Laudantium ipsa eos qui ad et ea at id et. Accusamus officia explicabo odio. Omnis delectus consequatur quisquam. Deleniti nihil voluptatem et neque optio et. Assumenda explicabo natus similique nostrum et error. Ut ipsum dolore et. Delectus possimus aut labore aliquam.",
			"category": {
				"id": 8
			},
			"status": "draft",
			"createdAt": "2024-03-20T00:51:49.991Z"
		},
		{
			"id": 9,
			"title": "Repellendus Itaque Ut",
			"content": "Eum omnis odit voluptatibus. Distinctio quam incidunt id nihil tempore similique id eos suscipit. Et officia rerum molestiae alias cupiditate et. Nisi nisi fugit. Repellendus reprehenderit eius possimus veritatis minima. Qui consequatur omnis vel dolor quo. Magni accusantium eum et dolores id cumque est. Numquam culpa porro tempore. Sit accusantium ipsam molestiae sed ipsam ullam ullam eos reiciendis. Aut facilis provident eligendi in et dolor.",
			"category": {
				"id": 15
			},
			"status": "draft",
			"createdAt": "2022-11-14T23:05:34.856Z"
		},
		{
			"id": 10,
			"title": "Dolorum Labore Perspiciatis",
			"content": "Quidem voluptate voluptas accusamus quia error doloremque molestiae. Doloremque laboriosam sed aut et quas ut pariatur voluptatem eum. Incidunt officia est provident eum unde. Enim qui quia fugit qui et aliquam minima et. Consequatur labore perferendis sapiente. Quos aut illo dicta qui sed minima. Non fugiat numquam repudiandae fuga vel enim cumque explicabo deleniti. Sit inventore veniam fugiat. Et laboriosam maiores nam deserunt necessitatibus ut distinctio hic laboriosam. Adipisci aut tenetur voluptatem sed ducimus.",
			"category": {
				"id": 9
			},
			"status": "draft",
			"createdAt": "2022-09-21T07:43:10.769Z"
		},
		{
			"id": 11,
			"title": "Tempore Reiciendis Repellendus",
			"content": "Fugit debitis ut amet consectetur. Sit est corporis reiciendis nobis aut id totam. Et debitis eligendi consequuntur natus eius fuga perferendis dicta dolorum. Debitis eveniet qui at sed reprehenderit consectetur eum repudiandae aperiam. Iste vel placeat quos enim occaecati et aut placeat. Accusantium perspiciatis dicta aspernatur. Sequi soluta quam officia enim aut exercitationem nemo quia et. Alias perferendis numquam. Ullam eum ipsa. Eum sapiente quis soluta dolorem reprehenderit eos.",
			"category": {
				"id": 6
			},
			"status": "rejected",
			"createdAt": "2024-04-06T22:57:11.452Z"
		},
		{
			"id": 12,
			"title": "Enim Voluptatum Reprehenderit",
			"content": "Ut totam quo. Ratione quia assumenda. Dolorem et ex ut qui quia maxime fugiat explicabo. Sed alias tempore qui sapiente molestiae odit. Atque nesciunt omnis officia saepe. Sunt facere minus in cumque temporibus debitis. Vel magni quae error sint. Facere veritatis ut. Expedita placeat totam exercitationem. Natus at at est optio quo magni inventore.",
			"category": {
				"id": 3
			},
			"status": "draft",
			"createdAt": "2022-06-05T02:36:29.203Z"
		},
		{
			"id": 13,
			"title": "Quas Officiis Aut",
			"content": "Consequatur eos rerum sunt quis alias voluptates nihil iure non. Sunt aliquam recusandae. Fugit odit consequuntur aut voluptas aut architecto dolor. Et eos laborum dolore rerum. Nulla excepturi corporis occaecati voluptas. Laborum id laboriosam voluptatem qui facilis quo. Expedita neque ex nobis neque doloremque et. Nesciunt temporibus et laborum. Est culpa quaerat facilis dolor ut quas beatae quia. Culpa dolorum deserunt similique et illo nobis quia.",
			"category": {
				"id": 4
			},
			"status": "draft",
			"createdAt": "2023-12-06T06:26:13.096Z"
		},
		{
			"id": 14,
			"title": "Esse Libero Tenetur",
			"content": "Aperiam aut necessitatibus iusto saepe velit. Nihil assumenda fuga cum amet. Omnis dolor sequi earum sapiente. Ut consequatur eos perspiciatis et eos. Voluptatem possimus officia neque est. Voluptas aut qui voluptatibus qui libero sit corrupti voluptas. Dignissimos et unde laboriosam quaerat aut explicabo ea vero. Voluptatem aut aperiam est nam. Qui architecto est voluptatem tempore voluptas. Eveniet omnis sed dolore architecto incidunt.",
			"category": {
				"id": 3
			},
			"status": "published",
			"createdAt": "2023-04-17T19:26:55.423Z"
		},
		{
			"id": 15,
			"title": "Nam Magni Fugiat",
			"content": "Corporis quia sint culpa non rerum aspernatur quod placeat. Aut voluptate officia et pariatur repudiandae. Est quasi enim quo aperiam earum temporibus minima quod asperiores. Ea neque quisquam. Perspiciatis quas expedita animi. Rem rem nulla similique quidem. Sint est dolores dolores maiores consequatur officia impedit corporis eligendi. Facere et dolore et dicta adipisci suscipit. Minus enim a voluptatem. Nesciunt deserunt velit.",
			"category": {
				"id": 13
			},
			"status": "draft",
			"createdAt": "2023-09-28T21:42:26.344Z"
		},
		{
			"id": 16,
			"title": "Voluptatem Autem Eligendi",
			"content": "Assumenda excepturi aut doloremque. Est iusto nostrum magnam eos. Maxime quas possimus adipisci in numquam eligendi. Numquam id et officiis aut perferendis qui ut. Libero odio et et deleniti. Enim illo quia consectetur nemo nobis distinctio. Eos est vitae totam. Et vitae id quia unde at. Nam minus aut. Aperiam officiis magnam rerum in sit perferendis veniam quia quis.",
			"category": {
				"id": 10
			},
			"status": "draft",
			"createdAt": "2023-08-10T20:16:43.285Z"
		},
		{
			"id": 17,
			"title": "Iusto Nobis Eligendi",
			"content": "Accusantium praesentium perspiciatis doloribus cum odio id animi. Modi fugit quia qui corporis qui odit. Dolorum qui accusamus placeat autem omnis rem qui. Est deserunt corporis voluptates. Animi vel a vel. Molestiae facilis error aut. Animi quas mollitia omnis aliquam. Iure error et. Assumenda est incidunt debitis. Repudiandae itaque dignissimos.",
			"category": {
				"id": 11
			},
			"status": "published",
			"createdAt": "2023-06-03T08:53:48.873Z"
		},
		{
			"id": 18,
			"title": "Nihil Et Id",
			"content": "Adipisci vero id facere est provident et voluptate commodi consectetur. Debitis omnis et maxime. Earum quasi officiis nihil illo omnis eligendi. Dolore iure nesciunt odio itaque. Et aperiam sequi nihil omnis. Aut dolorum ut id reiciendis. Consequatur ut libero praesentium voluptatibus. Corporis hic quisquam eos non enim atque officiis. Sint quam non voluptate facilis hic velit. Quaerat quidem eos rerum quisquam debitis quas perferendis aut voluptatibus.",
			"category": {
				"id": 1
			},
			"status": "rejected",
			"createdAt": "2024-03-10T08:14:19.370Z"
		},
		{
			"id": 19,
			"title": "Numquam Dolorem Reprehenderit",
			"content": "Id adipisci eveniet aut aut omnis veritatis autem eum et. Magnam saepe quia at in error iusto. Ut aperiam beatae aliquam. Non debitis quae saepe. Velit nemo et repellat provident ducimus amet omnis tempore quo. Eligendi ducimus consequatur aperiam dolor ullam. Eum soluta dolorem ipsam aut ab nulla qui. Nisi cumque quis iste corrupti aspernatur animi ullam soluta alias. Odit et dolores amet inventore molestiae reiciendis ipsum rem. Ullam vitae nulla consectetur nam occaecati reiciendis maiores.",
			"category": {
				"id": 2
			},
			"status": "published",
			"createdAt": "2024-03-01T00:43:19.564Z"
		},
		{
			"id": 20,
			"title": "Fugit Et Aut",
			"content": "Qui occaecati praesentium nemo at voluptas sequi. Dolores esse velit voluptas exercitationem omnis dolorem et temporibus minima. Velit qui dolorum amet eaque est aspernatur dolor occaecati. Enim sequi provident est consectetur quia minus temporibus. Enim et explicabo eveniet earum quae. Voluptate iste provident similique debitis laborum. Sit voluptatem fugit dignissimos expedita adipisci iusto libero. Perspiciatis id asperiores quisquam ab molestiae repellat quo ratione quam. Recusandae inventore est. Nostrum et sunt distinctio magni omnis architecto sunt.",
			"category": {
				"id": 4
			},
			"status": "rejected",
			"createdAt": "2022-11-19T20:10:22.536Z"
		},
		{
			"id": 21,
			"title": "Quae Eligendi Velit",
			"content": "Aperiam et sequi numquam vero maxime reiciendis similique ea maiores. Dolorem rerum veniam reprehenderit optio quia nam. Rerum eum veniam voluptatibus. Est suscipit et id et est officiis. Et nesciunt aut eum assumenda. Qui quo vel soluta et et. Deserunt sint quas dignissimos voluptatem in consequatur delectus. Eaque doloribus esse beatae necessitatibus maiores. Vel ratione illo aut alias. Fuga veniam sed ipsam corporis aliquid qui veritatis.",
			"category": {
				"id": 9
			},
			"status": "rejected",
			"createdAt": "2023-02-15T06:22:11.049Z"
		},
		{
			"id": 22,
			"title": "Nam Voluptatem Impedit",
			"content": "Aut ut eligendi tempora ut. Eligendi recusandae quasi non doloremque delectus distinctio. Sit voluptas pariatur illo illo numquam et. Qui non a minus qui et id. Et esse quis. Qui voluptate ut consectetur. Voluptatem dolore nam voluptas. Eos culpa a hic libero. Molestias eaque ea autem necessitatibus optio incidunt rerum sapiente. Corrupti quidem distinctio.",
			"category": {
				"id": 14
			},
			"status": "draft",
			"createdAt": "2022-06-16T07:20:28.959Z"
		},
		{
			"id": 23,
			"title": "Laudantium Magni Accusantium",
			"content": "Animi enim laborum eligendi. Ratione in doloribus eum. Recusandae amet aut ducimus perferendis excepturi a est vel autem. Dolorem animi et est assumenda incidunt reprehenderit. Dolores voluptatem est quaerat corporis aut perferendis autem non eveniet. Amet eos aliquid sunt dolor. Ut pariatur molestiae rerum. Inventore laborum sequi autem et ea sed adipisci sequi earum. Suscipit et vitae pariatur quis et explicabo quas. Tempore qui sequi omnis.",
			"category": {
				"id": 9
			},
			"status": "published",
			"createdAt": "2024-03-14T16:15:52.237Z"
		},
		{
			"id": 24,
			"title": "Illo Aliquam Ea",
			"content": "Et autem consectetur esse alias odio in dicta. Cum quo fugit placeat. Ut voluptate qui possimus atque et harum voluptatibus nulla. Quia aspernatur eum totam illum in numquam. Qui et sequi commodi fuga laboriosam voluptatem. Debitis a delectus qui debitis. Nesciunt quibusdam veniam debitis et similique nemo. Odit reiciendis id cumque magni nemo repellat veniam. Nam corrupti non est sequi dignissimos. Libero in laborum natus reiciendis laudantium dolorem rerum ipsa.",
			"category": {
				"id": 12
			},
			"status": "published",
			"createdAt": "2022-08-16T23:36:34.111Z"
		},
		{
			"id": 25,
			"title": "Non Et Facere",
			"content": "Aut non quo quod. Eius quo similique. Quasi sint repellat ut sequi velit possimus. Autem unde voluptatem mollitia et nobis consequatur voluptatibus rem exercitationem. Optio exercitationem voluptatibus perferendis ab ad illum dicta facilis asperiores. Quibusdam nobis odit autem quam quia non officiis dolorum inventore. Iure eaque expedita praesentium quia aut enim debitis in inventore. Debitis et aut. Et occaecati in voluptatem voluptas reiciendis repellendus voluptatem. Consequatur id sint ullam ut.",
			"category": {
				"id": 12
			},
			"status": "published",
			"createdAt": "2023-02-08T23:29:14.162Z"
		},
		{
			"id": 26,
			"title": "Deserunt Dicta Dolore",
			"content": "Dolorum voluptatibus excepturi. Voluptas dignissimos suscipit cumque id dignissimos et ut. Aspernatur quod optio est occaecati. Ex fugit illum ab quia. Nam dignissimos eligendi. Illo rerum rem non enim est ut. Ut sapiente est ex qui cum quas. Veniam architecto incidunt praesentium praesentium. Non eius reprehenderit eligendi est sed eaque. Laboriosam perferendis commodi pariatur sed est non.",
			"category": {
				"id": 8
			},
			"status": "rejected",
			"createdAt": "2023-10-20T08:24:27.847Z"
		},
		{
			"id": 27,
			"title": "Ducimus Non Corrupti",
			"content": "Maxime exercitationem autem quasi distinctio id dolorem. Atque nam consequuntur sed beatae. Sequi quam temporibus neque quia cumque doloremque incidunt. Magnam cupiditate vitae debitis nulla. Omnis et ipsa quam et earum non dolorem sint voluptas. Sapiente nemo modi eum qui sit aut. Enim molestiae impedit dolorem ab. Sed eos ea distinctio quibusdam repudiandae. Enim qui ut recusandae expedita dignissimos ut et. Non expedita illum aliquid vel.",
			"category": {
				"id": 8
			},
			"status": "rejected",
			"createdAt": "2022-06-14T08:59:26.714Z"
		},
		{
			"id": 28,
			"title": "Veniam Est Repudiandae",
			"content": "Consequatur nulla sed ab nesciunt necessitatibus. Illum voluptatibus officia. Corrupti et vitae quas minima nesciunt. Est sit quia voluptas ab quis ut. Dolor fugit fugiat reprehenderit. Animi dolor sunt quibusdam voluptas excepturi facilis dolorum. Est animi ipsa error aliquid est nobis aliquam voluptatem sunt. Soluta praesentium accusantium nam. Laboriosam sint dolorem est qui rem. Voluptatem dolorem molestias odio esse ut assumenda dolore ut.",
			"category": {
				"id": 15
			},
			"status": "rejected",
			"createdAt": "2023-05-24T12:17:21.091Z"
		},
		{
			"id": 29,
			"title": "Voluptatem Maiores Temporibus",
			"content": "Sed velit magni neque dolore minima iusto qui dolore. Ut asperiores ea tempora voluptas cupiditate enim. Autem aliquam et eveniet nostrum. Est minima quia eum. Porro sint quasi ducimus et aspernatur autem voluptatum voluptatem. Ab commodi quas in vero esse enim sit saepe veniam. Distinctio qui quibusdam omnis. Consequatur quo dolorem. Voluptas ea aut consequatur sit recusandae dolor. Quaerat qui earum.",
			"category": {
				"id": 8
			},
			"status": "draft",
			"createdAt": "2024-03-01T14:54:02.015Z"
		},
		{
			"id": 30,
			"title": "Exercitationem Commodi Eos",
			"content": "Veniam aperiam expedita cumque veritatis accusamus repellat. Corrupti beatae et. Adipisci incidunt quibusdam nobis. Laudantium maiores qui voluptatem voluptas ducimus temporibus est delectus. Sint enim dolore consequatur pariatur vero suscipit natus. Quis voluptatem cumque reiciendis quaerat enim et autem. Omnis et incidunt quia quasi tempora. Pariatur pariatur blanditiis eius. Ex non eos voluptas est totam fuga aut. Sint voluptatem quasi non.",
			"category": {
				"id": 11
			},
			"status": "draft",
			"createdAt": "2023-02-06T04:54:57.875Z"
		},
		{
			"id": 31,
			"title": "Totam Voluptates Officiis",
			"content": "Qui aut fugiat nostrum magnam sed. Deleniti nisi sed. Voluptate dolor reiciendis veritatis maxime. Quia reprehenderit reprehenderit odio velit nostrum itaque. Beatae sequi accusamus itaque fuga. Rerum deleniti saepe eum sint ut. Praesentium pariatur deserunt facere eos voluptas quod hic. Consectetur vel at architecto voluptatem tenetur eligendi autem dolores. Minima est quo quod ea consequatur aut. Enim laudantium quaerat incidunt qui occaecati nam ut.",
			"category": {
				"id": 8
			},
			"status": "draft",
			"createdAt": "2023-07-10T09:32:47.729Z"
		},
		{
			"id": 32,
			"title": "Autem Voluptatibus Non",
			"content": "Numquam maxime saepe est exercitationem inventore. Et vero dolor sed. Sed libero ut omnis. Minima quia harum velit accusamus rerum et. Repudiandae cum rerum sunt qui odit animi dignissimos labore. Magnam esse possimus voluptates necessitatibus dolorum et porro totam. Voluptatem beatae sed eum inventore hic. Voluptates consequatur aut eos molestias aliquid. Qui repellendus officiis laborum ipsam. Omnis et repudiandae dolor possimus hic eligendi.",
			"category": {
				"id": 11
			},
			"status": "rejected",
			"createdAt": "2023-01-04T18:48:57.802Z"
		},
		{
			"id": 33,
			"title": "Quia Excepturi Dicta",
			"content": "Accusamus alias ut labore enim. Aspernatur eius similique ea accusamus. Adipisci qui veniam odit libero repellat commodi. Ducimus corrupti recusandae qui unde aut molestias officia nemo non. Ut praesentium quos. Nisi dolor est in. Id tempore sint velit ad repellendus dolorem. Laudantium ullam sint repudiandae non cumque sapiente. Doloribus aut rem. Harum sint consequatur ut dignissimos similique amet.",
			"category": {
				"id": 2
			},
			"status": "rejected",
			"createdAt": "2022-06-30T14:40:59.308Z"
		},
		{
			"id": 34,
			"title": "Doloribus Accusantium Commodi",
			"content": "Esse magni quod voluptate. Est itaque voluptatibus sequi consectetur qui. Est eum corrupti debitis. Ut dolore officia blanditiis qui sit architecto doloremque. Animi rerum sed qui qui facere. Sit nulla voluptate illo rem occaecati. Et eaque vitae alias quos optio. Qui deserunt totam saepe ipsum necessitatibus voluptas. Voluptas et eum maiores quo. Saepe officiis minima maxime eligendi quidem tempora.",
			"category": {
				"id": 5
			},
			"status": "rejected",
			"createdAt": "2024-02-04T21:35:19.627Z"
		},
		{
			"id": 35,
			"title": "Aut Laudantium Saepe",
			"content": "Ea debitis vel amet et. Architecto quibusdam possimus dignissimos sed quidem libero eos ipsam exercitationem. Aut velit qui vel libero quod omnis quis amet. Aut laudantium necessitatibus laborum est excepturi sunt accusantium ut. Laborum aut voluptatem incidunt laborum. Veniam eveniet itaque et quos. Doloremque nesciunt ut. Voluptatem accusamus delectus eos et. Qui incidunt tempore. Consequuntur similique et sed omnis.",
			"category": {
				"id": 9
			},
			"status": "rejected",
			"createdAt": "2024-04-23T23:18:04.047Z"
		},
		{
			"id": 36,
			"title": "Aperiam Et Nam",
			"content": "Natus nobis quo tempora nobis. Occaecati quod et. Deserunt tempore ab odit ad est. Aperiam incidunt nam. Est officia et nihil sed ipsam id. Aspernatur explicabo accusantium quam. Doloribus eum explicabo architecto animi molestiae dicta. Voluptatem minima et sint sunt voluptatem molestiae. Est ut et minima voluptate sed ipsam. Reiciendis neque quo ut in quod consectetur.",
			"category": {
				"id": 5
			},
			"status": "draft",
			"createdAt": "2023-12-19T11:43:48.237Z"
		}
	]
}
